openformsclient/__init__.py
openformsclient/admin.py
openformsclient/apps.py
openformsclient/client.py
openformsclient/models.py
openformsclient/utils.py
openformsclient/migrations/0001_initial.py
openformsclient/migrations/0002_alter_configuration_options.py
openformsclient/migrations/0003_configuration_client_timeout.py
openformsclient/migrations/__init__.py
openformsclient/templates/openformsclient/templatetags/openforms_form.html
openformsclient/templates/openformsclient/templatetags/openforms_sdk_css.html
openformsclient/templates/openformsclient/templatetags/openforms_sdk_js.html
openformsclient/templates/openformsclient/templatetags/openforms_sdk_media.html
openformsclient/templatetags/__init__.py
openformsclient/templatetags/openforms.py
django_open_forms_client-0.4.0.dist-info/LICENSE
django_open_forms_client-0.4.0.dist-info/METADATA
django_open_forms_client-0.4.0.dist-info/WHEEL
django_open_forms_client-0.4.0.dist-info/top_level.txt
django_open_forms_client-0.4.0.dist-info/RECORD
